[
	{
		"flavor": "",
		"hook": "",
		"importance": "",
		"localHookTemplate": "",
		"name": "PRFmodel",
		"pathPlacement": "append",
		"subfolder": "",
		"toolboxRoot": "",
		"type": "include",
		"update": "",
		"url": ""
	},
	{
		"flavor": "",
		"hook": "",
		"importance": "",
		"localHookTemplate": "",
		"name": "BCBLViennaSoft",
		"pathPlacement": "prepend",
		"subfolder": "",
		"toolboxRoot": "",
		"type": "git",
		"update": "",
		"url": "https://github.com/garikoitz/BCBLViennaSoft.git"
	}
]
